{
  "latest-version": [
    {
      "stable": {
        "frontend": {
          "version": "0.1.0",
          "download-url": {
            "china": "PLACEHOLDER_FRONTEND_CHINA_URL",
            "global": "PLACEHOLDER_FRONTEND_GLOBAL_URL"
          }
        },
        "backend": {
          "version": "0.1.0",
          "download-url": {
            "china": "PLACEHOLDER_BACKEND_CHINA_URL",
            "global": "PLACEHOLDER_BACKEND_GLOBAL_URL"
          }
        }
      }
    },
    {
      "beta": {
        "frontend": {
          "version": "0.1.1",
          "download-url": {
            "china": "PLACEHOLDER_FRONTEND_BETA_CHINA_URL",
            "global": "PLACEHOLDER_FRONTEND_BETA_GLOBAL_URL"
          }
        },
        "backend": {
          "version": "0.1.1",
          "download-url": {
            "china": "PLACEHOLDER_BACKEND_BETA_CHINA_URL",
            "global": "PLACEHOLDER_BACKEND_BETA_GLOBAL_URL"
          }
        }
      }
    }
  ]
}
